LICENSE
MANIFEST.in
README.rst
requirements.txt
setup.cfg
setup.py
dash.py.egg-info/PKG-INFO
dash.py.egg-info/SOURCES.txt
dash.py.egg-info/dependency_links.txt
dash.py.egg-info/entry_points.txt
dash.py.egg-info/requires.txt
dash.py.egg-info/top_level.txt
dash_py/__init__.py
dash_py/cli.py
dash_py/installer.py
dash_py/utils.py
dash_py/packages/flask.yaml
dash_py/packages/jinja2.yaml